notionsdk/Client.py
notionsdk/Database.py
notionsdk/Model.py
notionsdk/Search.py
notionsdk/__init__.py
notyon/Client.py
notyon/Database.py
notyon/Model.py
notyon/Search.py
notyon/__init__.py
src/Client.py
src/Database.py
src/__init__.py
notyon-0.1.7.dist-info/LICENSE
notyon-0.1.7.dist-info/METADATA
notyon-0.1.7.dist-info/WHEEL
notyon-0.1.7.dist-info/top_level.txt
notyon-0.1.7.dist-info/RECORD
