Metadata-Version: 2.1
Name: notyon
Version: 0.1.7
Summary: Notion API implementation for Python
Home-page: https://gitlab.com/guilhermigg/notyon
Download-URL: https://gitlab.com/guilhermigg/notyon
Author: guilhermigg
Author-email: guilhermigg@protonmail.com
License: MIT
Keywords: notion,api,notyon,sdk,Notion API,notionsdk
Platform: UNKNOWN
Classifier: Development Status :: 3 - Alpha
Classifier: Intended Audience :: Developers
Classifier: License :: OSI Approved :: MIT License
Classifier: Programming Language :: Python :: 3
License-File: LICENSE
Requires-Dist: requests
Provides-Extra: dev
Requires-Dist: pytest (>=3.7) ; extra == 'dev'
